{
  "pageSize": 10,
  "projects": [
    { "id": "p-ip-001", "name": "28Y618攻略&流程指南", "domain": "营销", "priority": "P0", "owner": "徐健", "execUnit": "👤 徐健 + 🤖 Max", "period": "6/1–6/7", "kanbanStatus": "进行中", "progress": "流程指南主框架已定，Max 批量输出渠道延展稿中" },
    { "id": "p-ip-002", "name": "App16.0 品牌推广编排试点", "domain": "品牌", "priority": "P0", "owner": "欧阳蓓", "execUnit": "👤 欧阳蓓 + 🤖 Iris", "period": "6/3–6/14", "kanbanStatus": "进行中", "progress": "T1 叙事框架 G1 已过，主 KV 探索稿 3 方向待 G2" },
    { "id": "p-ip-003", "name": "28Y618 T1-引导系统流程体验", "domain": "互动", "priority": "P0", "owner": "翁婷", "execUnit": "👤 翁婷 + 🤖 Zig", "period": "6/2–6/10", "kanbanStatus": "进行中", "progress": "引导系统整合推进，弹窗/PUSH 视觉交互输出中" },
    { "id": "p-ip-004", "name": "28Y618主会场-万店秒杀日", "domain": "营销", "priority": "P0", "owner": "蔡璐", "execUnit": "🤖 Max → 👤 蔡璐", "period": "6/4–6/8", "kanbanStatus": "进行中", "progress": "主视觉锁定，多尺寸批量化待 G3 规范预检" },
    { "id": "p-ip-005", "name": "官方会场改版方案", "domain": "营销", "priority": "P0", "owner": "徐健", "execUnit": "👤 徐健", "period": "6/5–6/12", "kanbanStatus": "进行中", "progress": "改版方案探索中，信息层级与模块节奏待评审" },
    { "id": "p-ip-006", "name": "营销素材一键多尺寸 Copilot 试点", "domain": "营销", "priority": "P1", "owner": "王蕾", "execUnit": "🤖 Rio", "period": "6/1–6/15", "kanbanStatus": "进行中", "progress": "L3 可委派试运行，首稿通过率基线采集中" },
    { "id": "p-ip-007", "name": "编排层看板字段落地", "domain": "通用", "priority": "P1", "owner": "欧阳蓓", "execUnit": "👤 欧阳蓓", "period": "6/1–6/20", "kanbanStatus": "进行中", "progress": "执行单元 / skill_policy / human_gate 字段已入看板" },
    { "id": "p-ip-008", "name": "品牌/IP 资产生成式工作流", "domain": "品牌", "priority": "P1", "owner": "谭灿", "execUnit": "🤖 Finn → 👤 谭灿", "period": "6/3–6/18", "kanbanStatus": "进行中", "progress": "Joy 情绪资产 Prompt 母库整理，多场景变体测试中" },
    { "id": "p-ip-009", "name": "招商系统改版", "domain": "互动", "priority": "P1", "owner": "翁婷", "execUnit": "👤 翁婷", "period": "6/6–6/20", "kanbanStatus": "进行中", "progress": "前期沟通完成，需求文档与流程图梳理中" },
    { "id": "p-ip-010", "name": "主站互动-营销互动设计体验 AI 生成", "domain": "互动", "priority": "P0", "owner": "翁婷", "execUnit": "🤖 Zig → 👤 翁婷", "period": "6/1–6/9", "kanbanStatus": "进行中", "progress": "动态反馈方案 2 版待体验评审" },
    { "id": "p-ip-011", "name": "28Y618-万店狂欢会场", "domain": "营销", "priority": "P0", "owner": "蔡璐", "execUnit": "👤 蔡璐 + 🤖 Max", "period": "6/3–6/7", "kanbanStatus": "进行中", "progress": "等待业务反馈，局部模块微调中" },
    { "id": "p-ip-012", "name": "设计系统-618 主题规范", "domain": "营销", "priority": "P1", "owner": "王蕾", "execUnit": "👤 王蕾 + 🤖 Dex", "period": "6/1–6/25", "kanbanStatus": "进行中", "progress": "618 色彩/组件 token 输出 70%，Design Wiki 同步中" },
    { "id": "p-ip-013", "name": "验证契约四级模板试点", "domain": "通用", "priority": "P1", "owner": "欧阳蓓", "execUnit": "👤 欧阳蓓 + 🤖 Hope", "period": "6/4–6/16", "kanbanStatus": "进行中", "progress": "L/M/H/exploratory 模板已挂载 3 个 Skill" },
    { "id": "p-ip-014", "name": "28Y618-球迷惊喜日", "domain": "营销", "priority": "P0", "owner": "徐健", "execUnit": "🤖 Max → 👤 徐健", "period": "6/5–6/9", "kanbanStatus": "进行中", "progress": "待轮走查，Quinn 规范预检报告已出" },
    { "id": "p-ip-015", "name": "搜推品专 618 换肤", "domain": "营销", "priority": "P0", "owner": "蔡璐", "execUnit": "👤 蔡璐 + 🤖 Gus", "period": "6/2–6/6", "kanbanStatus": "进行中", "progress": "换肤稿输出中，搜索/推荐双端适配" },
    { "id": "p-ip-016", "name": "分享图生成运营试点", "domain": "营销", "priority": "P1", "owner": "王蕾", "execUnit": "🤖 Sage", "period": "6/3–6/12", "kanbanStatus": "进行中", "progress": "运营一句话生成分享图，L2 协作模式验证" },
    { "id": "p-ip-017", "name": "高端立影页面互动预演", "domain": "多媒体", "priority": "P1", "owner": "谭灿", "execUnit": "👤 谭灿 + 🤖 Neo", "period": "6/4–6/14", "kanbanStatus": "进行中", "progress": "Vibe Coding 预演页 1 版，动效对齐评审中" },
    { "id": "p-ip-018", "name": "618 T互-小程序视觉交互", "domain": "互动", "priority": "P0", "owner": "翁婷", "execUnit": "🤖 Zig → 👤 翁婷", "period": "6/1–6/8", "kanbanStatus": "进行中", "progress": "小程序主链路视觉 80%，Lumi 兜底 Lottie 同步输出" },

    { "id": "p-wt-001", "name": "矩阵 app 品牌规范延展", "domain": "品牌", "priority": "P2", "owner": "谭灿", "execUnit": "🤖 Iris → 👤 谭灿", "period": "6/16–6/28", "kanbanStatus": "待启动", "progress": "待 App16.0 主站规范 G4 发布后启动" },
    { "id": "p-wt-002", "name": "多专家 Copilot 编组部署", "domain": "通用", "priority": "P1", "owner": "欧阳蓓", "execUnit": "👤 胥浩 + 🤖 Flux", "period": "7/1–7/31", "kanbanStatus": "待启动", "progress": "Phase 3 规划项，待 Kite 编排度量复盘完成" },
    { "id": "p-wt-003", "name": "Skill 升格机制上线", "domain": "通用", "priority": "P2", "owner": "欧阳蓓", "execUnit": "👤 欧阳蓓 + 🤖 Skye", "period": "6/20–7/5", "kanbanStatus": "待启动", "progress": "adhoc ≥3 次升格流程待开发" },
    { "id": "p-wt-004", "name": "外投&搜索品专二期改版", "domain": "营销", "priority": "P1", "owner": "蔡璐", "execUnit": "👤 蔡璐 + 🤖 Gus", "period": "6/15–6/25", "kanbanStatus": "待启动", "progress": "待一期数据复盘后立项" },
    { "id": "p-wt-005", "name": "28Y-官方会场搭建指南迭代", "domain": "营销", "priority": "P1", "owner": "徐健", "execUnit": "👤 徐健 + 🤖 Faye", "period": "6/18–6/30", "kanbanStatus": "待启动", "progress": "等待启动，需同步大促节奏" },
    { "id": "p-wt-006", "name": "618 T互玩法二期", "domain": "互动", "priority": "P1", "owner": "翁婷", "execUnit": "🤖 Gigi", "period": "6/20–7/10", "kanbanStatus": "待启动", "progress": "一期玩法数据待回收" },
    { "id": "p-wt-007", "name": "短剧/短视频 AI 工作流二期", "domain": "多媒体", "priority": "P2", "owner": "谭灿", "execUnit": "👤 谭灿 + 🤖 Cora", "period": "7/1–7/20", "kanbanStatus": "待启动", "progress": "分镜助手试点复盘后启动" },
    { "id": "p-wt-008", "name": "度量报告自动化", "domain": "通用", "priority": "P2", "owner": "欧阳蓓", "execUnit": "🤖 Mira", "period": "6/25–7/8", "kanbanStatus": "待启动", "progress": "首稿通过率 / 人机工时比字段待接入" },
    { "id": "p-wt-009", "name": "Joy 矩阵规范-ai购/到家", "domain": "品牌", "priority": "P2", "owner": "谭灿", "execUnit": "🤖 Jade", "period": "6/22–7/5", "kanbanStatus": "待启动", "progress": "主站规范终稿后并行启动" },
    { "id": "p-wt-010", "name": "互动小游戏 AI 生成二期", "domain": "互动", "priority": "P2", "owner": "翁婷", "execUnit": "🤖 Gigi", "period": "7/5–7/25", "kanbanStatus": "待启动", "progress": "研发验证链路待确认" },
    { "id": "p-wt-011", "name": "营销头图生成工具-品类扩展", "domain": "营销", "priority": "P2", "owner": "王蕾", "execUnit": "🤖 Hero", "period": "6/18–7/2", "kanbanStatus": "待启动", "progress": "3C/健康/时尚品类模板待补充" },
    { "id": "p-wt-012", "name": "Wiki 资产同步自动化", "domain": "通用", "priority": "P2", "owner": "欧阳蓓", "execUnit": "🤖 Wren → 👤 欧阳蓓", "period": "6/20–7/1", "kanbanStatus": "待启动", "progress": "workflow-wiki-asset-sync Skill 待发布" },

    { "id": "p-dn-001", "name": "28Y618主会场-超级品牌周", "domain": "营销", "priority": "P0", "owner": "蔡璐", "execUnit": "🤖 Max → 👤 蔡璐", "period": "5/28–6/2", "kanbanStatus": "已完成", "progress": "完成交付，G4 终审通过，资产已归档" },
    { "id": "p-dn-002", "name": "28Y京东618-频道视觉买一送一", "domain": "营销", "priority": "P0", "owner": "徐健", "execUnit": "👤 徐健", "period": "5/25–5/30", "kanbanStatus": "已完成", "progress": "完成交付，多尺寸套系已回填 Zero" },
    { "id": "p-dn-003", "name": "Design Wiki 可执行子集 v1", "domain": "通用", "priority": "P0", "owner": "欧阳蓓", "execUnit": "👤 欧阳蓓 + 🤖 Vera", "period": "5/1–5/20", "kanbanStatus": "已完成", "progress": "色彩/字体/1/9/命名规范已发布 v1.0" },
    { "id": "p-dn-004", "name": "结构化需求模板包", "domain": "通用", "priority": "P1", "owner": "欧阳蓓", "execUnit": "👤 欧阳蓓 + 🤖 Demi", "period": "5/10–5/25", "kanbanStatus": "已完成", "progress": "5 类模板上线：大促/规范/归档/wiki/互动" },
    { "id": "p-dn-005", "name": "AI 品牌 Brief 工具 v1", "domain": "品牌", "priority": "P1", "owner": "谭灿", "execUnit": "👤 谭灿 + 🤖 Bri", "period": "4/15–5/10", "kanbanStatus": "已完成", "progress": "完成交付，业务方 Brief 填写效率提升 100%" },
    { "id": "p-dn-006", "name": "Lottie 动效交付管道", "domain": "互动", "priority": "P0", "owner": "翁婷", "execUnit": "🤖 Lumi", "period": "4/20–5/15", "kanbanStatus": "已完成", "progress": "编辑器 v0.8 已应用，覆盖 80% 营销动效需求" },
    { "id": "p-dn-007", "name": "28Y618 3C数码日-t互收方图", "domain": "营销", "priority": "P0", "owner": "蔡璐", "execUnit": "🤖 Max → 👤 蔡璐", "period": "5/20–5/24", "kanbanStatus": "已完成", "progress": "完成交付，规范 lint 全绿" },
    { "id": "p-dn-008", "name": "品牌方案调研工作流 V1.2", "domain": "品牌", "priority": "P1", "owner": "谭灿", "execUnit": "👤 谭灿 + 🤖 Scout", "period": "3/1–4/30", "kanbanStatus": "已完成", "progress": "已应用，执行效率提升 700%" },
    { "id": "p-dn-009", "name": "商店功能介绍图多尺寸", "domain": "营销", "priority": "P0", "owner": "王蕾", "execUnit": "🤖 Pixel", "period": "4/1–4/20", "kanbanStatus": "已完成", "progress": "8 种尺寸 100+ 资源批量交付完成" },
    { "id": "p-dn-010", "name": "营销头图生成工具 V1.0", "domain": "营销", "priority": "P0", "owner": "王蕾", "execUnit": "🤖 Hero", "period": "3/15–4/10", "kanbanStatus": "已完成", "progress": "已应用，AI/模板双模式上线" },
    { "id": "p-dn-011", "name": "京东品牌样机工具", "domain": "品牌", "priority": "P1", "owner": "谭灿", "execUnit": "👤 谭灿 + 🤖 Nova", "period": "4/5–5/1", "kanbanStatus": "已完成", "progress": "Logo 上传生成提案样机能力已上线" },
    { "id": "p-dn-012", "name": "脚本及分镜生成助手试点", "domain": "多媒体", "priority": "P1", "owner": "谭灿", "execUnit": "🤖 Cora", "period": "5/1–5/20", "kanbanStatus": "已完成", "progress": "剧本→分镜画布全流程跑通 1 条案例" },
    { "id": "p-dn-013", "name": "质检回流机制文档", "domain": "通用", "priority": "P1", "owner": "欧阳蓓", "execUnit": "👤 欧阳蓓 + 🤖 Echo", "period": "5/15–5/28", "kanbanStatus": "已完成", "progress": "返工原因标签体系与回流 SOP 已发布" },
    { "id": "p-dn-014", "name": "分享图生成 MVP", "domain": "营销", "priority": "P1", "owner": "王蕾", "execUnit": "🤖 Sage", "period": "5/8–5/25", "kanbanStatus": "已完成", "progress": "运营一句话生成分享图，MVP 验收通过" }
  ]
}
